mathterpreter/__init__.py
mathterpreter/__main__.py
mathterpreter/_parser.py
mathterpreter/cli.py
mathterpreter/exceptions.py
mathterpreter/lexer.py
mathterpreter/main.py
mathterpreter/nodes.py
mathterpreter/tokens.py
mathterpreter-1.1.2.dist-info/LICENSE
mathterpreter-1.1.2.dist-info/METADATA
mathterpreter-1.1.2.dist-info/WHEEL
mathterpreter-1.1.2.dist-info/entry_points.txt
mathterpreter-1.1.2.dist-info/top_level.txt
mathterpreter-1.1.2.dist-info/RECORD
