Metadata-Version: 2.1
Name: mathterpreter
Version: 1.1.2
Summary: A lightweight and basic maths interpreter
Home-page: https://github.com/pjones123/mathterpreter
Author: pjones123
License: MIT
Keywords: python,math,maths
Platform: UNKNOWN
Classifier: Programming Language :: Python :: 3.7
Requires-Dist: dataclasses
